LICENSE.md
function_pipes/__init__.py
function_pipes/pipes.jinja-py
function_pipes/py.typed
function_pipes/with_paramspec/function_pipes.py
function_pipes/without_paramspec/function_pipes.py
function_pipes-0.1.2.dist-info/LICENSE.md
function_pipes-0.1.2.dist-info/WHEEL
function_pipes-0.1.2.dist-info/METADATA
function_pipes-0.1.2.dist-info/RECORD
