Metadata-Version: 2.1
Name: function-pipes
Version: 0.1.2
Summary: Typed python equivalent for R pipes.
Home-page: https://github.com/ajparsons/function-pipes
License: MIT
Author: Alex Parsons
Author-email: alex@alexparsons.co.uk
Requires-Python: >=3.8,<4.0
Classifier: License :: OSI Approved :: MIT License
Classifier: Programming Language :: Python :: 3
Classifier: Programming Language :: Python :: 3.8
Classifier: Programming Language :: Python :: 3.9
Classifier: Programming Language :: Python :: 3.10
Classifier: Programming Language :: Python :: 3.11
Project-URL: Repository, https://github.com/ajparsons/function-pipes
